llm_mimetypes/__init__.py
llm_mimetypes/by_mime_type.py
llm_mimetypes/by_model.py
llm_mimetypes/by_provider.py
llm_mimetypes/file.py
llm_mimetypes/data/__init__.py
llm_mimetypes/data/models.db
llm_mimetypes-0.1.0.dist-info/METADATA
llm_mimetypes-0.1.0.dist-info/WHEEL
llm_mimetypes-0.1.0.dist-info/entry_points.txt
llm_mimetypes-0.1.0.dist-info/RECORD
